mqtt2mqtt/__init__.py
mqtt2mqtt/cli.py
mqtt2mqtt/config.py
mqtt2mqtt/mqtt2mqtt.py
mqtt2mqtt-0.1.0.dist-info/METADATA
mqtt2mqtt-0.1.0.dist-info/RECORD
mqtt2mqtt-0.1.0.dist-info/WHEEL
mqtt2mqtt-0.1.0.dist-info/entry_points.txt
mqtt2mqtt-0.1.0.dist-info/top_level.txt
